{
  "id": "research-go-frameworks",
  "subject": "Research Go web frameworks and ecosystem gaps",
  "description": "Investigate Go web frameworks: Echo, Fiber, Gin, Chi, Buffalo, Huma, Encore, Temporal. What patterns exist? What's missing vs JS frameworks? What would a \"fullstack\" Go framework need that doesn't exist yet?",
  "activeForm": "Research Go web frameworks and ecosystem gaps",
  "status": "pending",
  "blocks": [
    "compile-draft"
  ],
  "blockedBy": [],
  "priority": "high",
  "tags": [],
  "fileRefs": [],
  "subtasks": [],
  "scope": "m",
  "notes": [],
  "history": [
    {
      "from": "pending",
      "to": "pending",
      "reason": "Created",
      "timestamp": "2026-05-05T20:55:09.835Z"
    }
  ]
}